{"nodes": [{"id": "springboot_src_main_java_com_chs_springboot_global_auth_repository_useraccountrepository_java", "label": "UserAccountRepository.java", "file_type": "code", "source_file": "springboot\\src\\main\\java\\com\\chs\\springboot\\global\\auth\\repository\\UserAccountRepository.java", "source_location": "L1"}, {"id": "useraccountrepository_useraccountrepository", "label": "UserAccountRepository", "file_type": "code", "source_file": "springboot\\src\\main\\java\\com\\chs\\springboot\\global\\auth\\repository\\UserAccountRepository.java", "source_location": "L9"}, {"id": "useraccountrepository_useraccountrepository_findbyemail", "label": ".findByEmail()", "file_type": "code", "source_file": "springboot\\src\\main\\java\\com\\chs\\springboot\\global\\auth\\repository\\UserAccountRepository.java", "source_location": "L10"}], "edges": [{"source": "springboot_src_main_java_com_chs_springboot_global_auth_repository_useraccountrepository_java", "target": "useraccount", "relation": "imports", "confidence": "EXTRACTED", "source_file": "springboot\\src\\main\\java\\com\\chs\\springboot\\global\\auth\\repository\\UserAccountRepository.java", "source_location": "L4", "weight": 1.0}, {"source": "springboot_src_main_java_com_chs_springboot_global_auth_repository_useraccountrepository_java", "target": "jparepository", "relation": "imports", "confidence": "EXTRACTED", "source_file": "springboot\\src\\main\\java\\com\\chs\\springboot\\global\\auth\\repository\\UserAccountRepository.java", "source_location": "L5", "weight": 1.0}, {"source": "springboot_src_main_java_com_chs_springboot_global_auth_repository_useraccountrepository_java", "target": "optional", "relation": "imports", "confidence": "EXTRACTED", "source_file": "springboot\\src\\main\\java\\com\\chs\\springboot\\global\\auth\\repository\\UserAccountRepository.java", "source_location": "L7", "weight": 1.0}, {"source": "springboot_src_main_java_com_chs_springboot_global_auth_repository_useraccountrepository_java", "target": "useraccountrepository_useraccountrepository", "relation": "contains", "confidence": "EXTRACTED", "source_file": "springboot\\src\\main\\java\\com\\chs\\springboot\\global\\auth\\repository\\UserAccountRepository.java", "source_location": "L9", "weight": 1.0}, {"source": "useraccountrepository_useraccountrepository", "target": "useraccountrepository_useraccountrepository_findbyemail", "relation": "method", "confidence": "EXTRACTED", "source_file": "springboot\\src\\main\\java\\com\\chs\\springboot\\global\\auth\\repository\\UserAccountRepository.java", "source_location": "L10", "weight": 1.0}]}