{"nodes": [{"id": "nexus_tests_debug_model_availability_py", "label": "debug_model_availability.py", "file_type": "code", "source_file": "nexus\\tests\\debug_model_availability.py", "source_location": "L1"}, {"id": "debug_model_availability_call_model", "label": "call_model()", "file_type": "code", "source_file": "nexus\\tests\\debug_model_availability.py", "source_location": "L46"}, {"id": "debug_model_availability_print_result", "label": "print_result()", "file_type": "code", "source_file": "nexus\\tests\\debug_model_availability.py", "source_location": "L70"}, {"id": "debug_model_availability_section", "label": "section()", "file_type": "code", "source_file": "nexus\\tests\\debug_model_availability.py", "source_location": "L79"}, {"id": "debug_model_availability_list_models", "label": "list_models()", "file_type": "code", "source_file": "nexus\\tests\\debug_model_availability.py", "source_location": "L87"}, {"id": "debug_model_availability_run_url_context", "label": "run_url_context()", "file_type": "code", "source_file": "nexus\\tests\\debug_model_availability.py", "source_location": "L97"}, {"id": "debug_model_availability_run_quiz", "label": "run_quiz()", "file_type": "code", "source_file": "nexus\\tests\\debug_model_availability.py", "source_location": "L105"}, {"id": "debug_model_availability_main", "label": "main()", "file_type": "code", "source_file": "nexus\\tests\\debug_model_availability.py", "source_location": "L151"}, {"id": "debug_model_availability_rationale_1", "label": "\ubaa8\ub378 \uac00\uc6a9\uc131 \ubc0f \ud488\uc9c8 \ud14c\uc2a4\ud2b8. url_context \ube0c\ub77c\uc6b0\uc9d5 + quiz \ud568\uc218(explain_word, generate_quiz stage 1/", "file_type": "rationale", "source_file": "nexus\\tests\\debug_model_availability.py", "source_location": "L1"}], "edges": [{"source": "nexus_tests_debug_model_availability_py", "target": "asyncio", "relation": "imports", "confidence": "EXTRACTED", "source_file": "nexus\\tests\\debug_model_availability.py", "source_location": "L11", "weight": 1.0}, {"source": "nexus_tests_debug_model_availability_py", "target": "os", "relation": "imports", "confidence": "EXTRACTED", "source_file": "nexus\\tests\\debug_model_availability.py", "source_location": "L12", "weight": 1.0}, {"source": "nexus_tests_debug_model_availability_py", "target": "sys", "relation": "imports", "confidence": "EXTRACTED", "source_file": "nexus\\tests\\debug_model_availability.py", "source_location": "L13", "weight": 1.0}, {"source": "nexus_tests_debug_model_availability_py", "target": "time", "relation": "imports", "confidence": "EXTRACTED", "source_file": "nexus\\tests\\debug_model_availability.py", "source_location": "L14", "weight": 1.0}, {"source": "nexus_tests_debug_model_availability_py", "target": "google", "relation": "imports_from", "confidence": "EXTRACTED", "source_file": "nexus\\tests\\debug_model_availability.py", "source_location": "L18", "weight": 1.0}, {"source": "nexus_tests_debug_model_availability_py", "target": "google_genai", "relation": "imports_from", "confidence": "EXTRACTED", "source_file": "nexus\\tests\\debug_model_availability.py", "source_location": "L19", "weight": 1.0}, {"source": "nexus_tests_debug_model_availability_py", "target": "config", "relation": "imports_from", "confidence": "EXTRACTED", "source_file": "nexus\\tests\\debug_model_availability.py", "source_location": "L20", "weight": 1.0}, {"source": "nexus_tests_debug_model_availability_py", "target": "debug_model_availability_call_model", "relation": "contains", "confidence": "EXTRACTED", "source_file": "nexus\\tests\\debug_model_availability.py", "source_location": "L46", "weight": 1.0}, {"source": "nexus_tests_debug_model_availability_py", "target": "debug_model_availability_print_result", "relation": "contains", "confidence": "EXTRACTED", "source_file": "nexus\\tests\\debug_model_availability.py", "source_location": "L70", "weight": 1.0}, {"source": "nexus_tests_debug_model_availability_py", "target": "debug_model_availability_section", "relation": "contains", "confidence": "EXTRACTED", "source_file": "nexus\\tests\\debug_model_availability.py", "source_location": "L79", "weight": 1.0}, {"source": "nexus_tests_debug_model_availability_py", "target": "debug_model_availability_list_models", "relation": "contains", "confidence": "EXTRACTED", "source_file": "nexus\\tests\\debug_model_availability.py", "source_location": "L87", "weight": 1.0}, {"source": "nexus_tests_debug_model_availability_py", "target": "debug_model_availability_run_url_context", "relation": "contains", "confidence": "EXTRACTED", "source_file": "nexus\\tests\\debug_model_availability.py", "source_location": "L97", "weight": 1.0}, {"source": "nexus_tests_debug_model_availability_py", "target": "debug_model_availability_run_quiz", "relation": "contains", "confidence": "EXTRACTED", "source_file": "nexus\\tests\\debug_model_availability.py", "source_location": "L105", "weight": 1.0}, {"source": "nexus_tests_debug_model_availability_py", "target": "debug_model_availability_main", "relation": "contains", "confidence": "EXTRACTED", "source_file": "nexus\\tests\\debug_model_availability.py", "source_location": "L151", "weight": 1.0}, {"source": "debug_model_availability_run_url_context", "target": "debug_model_availability_section", "relation": "calls", "confidence": "EXTRACTED", "source_file": "nexus\\tests\\debug_model_availability.py", "source_location": "L99", "weight": 1.0}, {"source": "debug_model_availability_run_url_context", "target": "debug_model_availability_call_model", "relation": "calls", "confidence": "EXTRACTED", "source_file": "nexus\\tests\\debug_model_availability.py", "source_location": "L101", "weight": 1.0}, {"source": "debug_model_availability_run_url_context", "target": "debug_model_availability_print_result", "relation": "calls", "confidence": "EXTRACTED", "source_file": "nexus\\tests\\debug_model_availability.py", "source_location": "L102", "weight": 1.0}, {"source": "debug_model_availability_run_quiz", "target": "debug_model_availability_section", "relation": "calls", "confidence": "EXTRACTED", "source_file": "nexus\\tests\\debug_model_availability.py", "source_location": "L145", "weight": 1.0}, {"source": "debug_model_availability_run_quiz", "target": "debug_model_availability_call_model", "relation": "calls", "confidence": "EXTRACTED", "source_file": "nexus\\tests\\debug_model_availability.py", "source_location": "L147", "weight": 1.0}, {"source": "debug_model_availability_run_quiz", "target": "debug_model_availability_print_result", "relation": "calls", "confidence": "EXTRACTED", "source_file": "nexus\\tests\\debug_model_availability.py", "source_location": "L148", "weight": 1.0}, {"source": "debug_model_availability_main", "target": "debug_model_availability_run_url_context", "relation": "calls", "confidence": "EXTRACTED", "source_file": "nexus\\tests\\debug_model_availability.py", "source_location": "L158", "weight": 1.0}, {"source": "debug_model_availability_main", "target": "debug_model_availability_run_quiz", "relation": "calls", "confidence": "EXTRACTED", "source_file": "nexus\\tests\\debug_model_availability.py", "source_location": "L159", "weight": 1.0}, {"source": "debug_model_availability_rationale_1", "target": "nexus_tests_debug_model_availability_py", "relation": "rationale_for", "confidence": "EXTRACTED", "source_file": "nexus\\tests\\debug_model_availability.py", "source_location": "L1", "weight": 1.0}]}