{"nodes": [{"id": "signal_page_signalpage_jsx", "label": "SignalPage.jsx - Signal Dashboard Main Page", "file_type": "document", "source_file": "frontend/src/page/signal/signal-page.md", "source_location": null, "source_url": null, "captured_at": null, "author": null, "contributor": null}, {"id": "signal_page_usesignalsse", "label": "useSignalSse Hook - SSE Data Stream", "file_type": "document", "source_file": "frontend/src/page/signal/signal-page.md", "source_location": null, "source_url": null, "captured_at": null, "author": null, "contributor": null}, {"id": "signal_page_sse_endpoint", "label": "SSE Endpoint /api/signal/stream/sse", "file_type": "document", "source_file": "frontend/src/page/signal/signal-page.md", "source_location": null, "source_url": null, "captured_at": null, "author": null, "contributor": null}, {"id": "signal_page_rest_init", "label": "REST API /api/signal/init", "file_type": "document", "source_file": "frontend/src/page/signal/signal-page.md", "source_location": null, "source_url": null, "captured_at": null, "author": null, "contributor": null}, {"id": "signal_page_rest_history", "label": "REST API /api/signal/history", "file_type": "document", "source_file": "frontend/src/page/signal/signal-page.md", "source_location": null, "source_url": null, "captured_at": null, "author": null, "contributor": null}, {"id": "signal_page_grid_layout", "label": "Signal Dashboard 12-Column Grid Layout", "file_type": "document", "source_file": "frontend/src/page/signal/signal-page.md", "source_location": null, "source_url": null, "captured_at": null, "author": null, "contributor": null}], "edges": [{"source": "signal_page_signalpage_jsx", "target": "signal_components_topbar", "relation": "references", "confidence": "EXTRACTED", "confidence_score": 1.0, "source_file": "frontend/src/page/signal/signal-page.md", "source_location": null, "weight": 1.0}, {"source": "signal_page_signalpage_jsx", "target": "signal_components_longpanel", "relation": "references", "confidence": "EXTRACTED", "confidence_score": 1.0, "source_file": "frontend/src/page/signal/signal-page.md", "source_location": null, "weight": 1.0}, {"source": "signal_page_signalpage_jsx", "target": "signal_components_shortpanel", "relation": "references", "confidence": "EXTRACTED", "confidence_score": 1.0, "source_file": "frontend/src/page/signal/signal-page.md", "source_location": null, "weight": 1.0}, {"source": "signal_page_signalpage_jsx", "target": "signal_components_maincore", "relation": "references", "confidence": "EXTRACTED", "confidence_score": 1.0, "source_file": "frontend/src/page/signal/signal-page.md", "source_location": null, "weight": 1.0}, {"source": "signal_page_signalpage_jsx", "target": "signal_components_liquidationpanel", "relation": "references", "confidence": "EXTRACTED", "confidence_score": 1.0, "source_file": "frontend/src/page/signal/signal-page.md", "source_location": null, "weight": 1.0}, {"source": "signal_page_signalpage_jsx", "target": "signal_components_shortliqpanel", "relation": "references", "confidence": "EXTRACTED", "confidence_score": 1.0, "source_file": "frontend/src/page/signal/signal-page.md", "source_location": null, "weight": 1.0}, {"source": "signal_page_signalpage_jsx", "target": "signal_components_patternstrip", "relation": "references", "confidence": "EXTRACTED", "confidence_score": 1.0, "source_file": "frontend/src/page/signal/signal-page.md", "source_location": null, "weight": 1.0}, {"source": "signal_page_signalpage_jsx", "target": "signal_page_usesignalsse", "relation": "references", "confidence": "EXTRACTED", "confidence_score": 1.0, "source_file": "frontend/src/page/signal/signal-page.md", "source_location": null, "weight": 1.0}, {"source": "signal_page_signalpage_jsx", "target": "signal_components_time_ranges", "relation": "references", "confidence": "EXTRACTED", "confidence_score": 1.0, "source_file": "frontend/src/page/signal/signal-page.md", "source_location": null, "weight": 1.0}, {"source": "signal_page_signalpage_jsx", "target": "signal_page_grid_layout", "relation": "references", "confidence": "EXTRACTED", "confidence_score": 1.0, "source_file": "frontend/src/page/signal/signal-page.md", "source_location": null, "weight": 1.0}, {"source": "signal_page_usesignalsse", "target": "signal_page_sse_endpoint", "relation": "references", "confidence": "EXTRACTED", "confidence_score": 1.0, "source_file": "frontend/src/page/signal/signal-page.md", "source_location": null, "weight": 1.0}, {"source": "signal_page_signalpage_jsx", "target": "signal_page_rest_init", "relation": "references", "confidence": "EXTRACTED", "confidence_score": 1.0, "source_file": "frontend/src/page/signal/signal-page.md", "source_location": null, "weight": 1.0}, {"source": "signal_page_signalpage_jsx", "target": "signal_page_rest_history", "relation": "references", "confidence": "EXTRACTED", "confidence_score": 1.0, "source_file": "frontend/src/page/signal/signal-page.md", "source_location": null, "weight": 1.0}, {"source": "signal_page_usesignalsse", "target": "trade_page_usebinancetradessse", "relation": "semantically_similar_to", "confidence": "INFERRED", "confidence_score": 0.75, "source_file": "frontend/src/page/signal/signal-page.md", "source_location": null, "weight": 0.75}], "hyperedges": [{"id": "signal_dashboard_component_tree", "label": "Signal Dashboard Component Hierarchy", "nodes": ["signal_page_signalpage_jsx", "signal_components_maincore", "signal_components_energygauge", "signal_components_tugofwar", "signal_components_minichartplaceholder", "signal_components_oilinechart", "signal_components_topbar", "signal_components_longpanel", "signal_components_shortpanel", "signal_components_liquidationpanel", "signal_components_shortliqpanel", "signal_components_patternstrip"], "relation": "implement", "confidence": "EXTRACTED", "confidence_score": 1.0, "source_file": "frontend/src/page/signal/signal-page.md"}, {"id": "binance_sse_sse_data_pipeline", "label": "Signal Dashboard SSE Real-time Data Pipeline", "nodes": ["signal_page_usesignalsse", "signal_page_sse_endpoint", "signal_page_signalpage_jsx", "signal_components_longpanel", "signal_components_shortpanel", "signal_components_liquidationpanel", "signal_components_shortliqpanel"], "relation": "participate_in", "confidence": "EXTRACTED", "confidence_score": 1.0, "source_file": "frontend/src/page/signal/signal-page.md"}]}